[
  {
    "id": "kiesel",
    "category": "Teamlead",
    "email": "Johannes.Kiesel@gesis.org",
    "name": ["Johannes", "Kiesel"],
    "orcid": "0000-0002-1617-6508",
    "title": "Dr.",
    "topics": ["Conversational AI", "Computational Argumentation", "Human Values", "Methods Hub", "User Simulation"],
    "url": "https://kiesels.de/johannes"
  },
  {
    "id": "chang",
    "category": "Staff",
    "email": "Po-Chun.Chang@gesis.org",
    "name": ["Po-Chun", "Chang"],
    "topics": ["Methods Hub"],
    "years": "2025 - today"
  },
  {
    "id": "khan",
    "category": "Staff",
    "email": "Taimoor.Khan@gesis.org",
    "name": ["Muhammad Taimoor", "Khan"],
    "orcid": "0000-0002-6542-9217",
    "title": "Dr.",
    "years": "2025 - today"
  },
  {
    "id": "linzbach",
    "category": "Staff",
    "email": "Stephan.Linzbach@gesis.org",
    "name": ["Stephan", "Linzbach"],
    "orcid": "0009-0009-6955-2368",
    "years": "2025 - today"
  },
  {
    "id": "momeni",
    "category": "Staff",
    "email": "Fakhri.Momeni@gesis.org",
    "name": ["Fakhri", "Momeni"],
    "orcid": "0000-0002-5572-575X",
    "title": "Dr.",
    "years": "2025 - today"
  },
  {
    "id": "muench",
    "category": "Staff",
    "email": "Felix.Muench@gesis.org",
    "name": ["Felix Viktor", "M\u00fcnch"],
    "orcid": "0000-0001-8808-6790",
    "title": "Dr.",
    "years": "2025 - today"
  },
  {
    "id": "rieger",
    "category": "Staff",
    "email": "Alisa.Rieger@gesis.org",
    "name": ["Alisa", "Rieger"],
    "orcid": "0000-0002-2274-1606",
    "title": "Dr.",
    "years": "2025 - today"
  },
  {
    "id": "yu",
    "category": "Staff",
    "email": "Ran.Yu@gesis.org",
    "name": ["Ran", "Yu"],
    "orcid": "0000-0002-1619-3164",
    "title": "Dr.",
    "years": "2025 - today"
  }
]
